__init__.py
default.py
sawan888-1.0.1.dist-info/LICENSE
sawan888-1.0.1.dist-info/METADATA
sawan888-1.0.1.dist-info/WHEEL
sawan888-1.0.1.dist-info/top_level.txt
sawan888-1.0.1.dist-info/RECORD
