Metadata-Version: 2.1
Name: sawan888
Version: 1.0.1
Summary: sawan888 เครือใหญ่ allslot 88 โปรทุนน้อยรับ100
Author-email: Sawan888 <sawan888@example.com>
Project-URL: Homepage, https://github.com/
Classifier: Programming Language :: Python :: 3
Classifier: License :: OSI Approved :: MIT License
Classifier: Operating System :: OS Independent
Requires-Python: >=3.7
License-File: LICENSE
